anonymizer/__init__.py
anonymizer/introspect.py
anonymizer/test_settings.py
anonymizer/models.py
anonymizer/replacers.py
anonymizer/base.py
anonymizer/tests/__init__.py
anonymizer/tests/models.py
anonymizer/management/__init__.py
anonymizer/management/commands/__init__.py
anonymizer/management/commands/anonymize_data.py
anonymizer/management/commands/create_anonymizers.py
django_anonymizer-0.5.1.dist-info/DESCRIPTION.rst
django_anonymizer-0.5.1.dist-info/metadata.json
django_anonymizer-0.5.1.dist-info/top_level.txt
django_anonymizer-0.5.1.dist-info/WHEEL
django_anonymizer-0.5.1.dist-info/RECORD
django_anonymizer-0.5.1.dist-info/METADATA
