Metadata-Version: 2.0
Name: django-anonymizer
Version: 0.5.1
Summary: App to anonymize data in Django models.
Home-page: https://github.com/BetterWorks/django-anonymizer
Author: David Stensland
Author-email: anonymizer@terite.com
License: MIT
Keywords: django data database anonymize private
Platform: UNKNOWN
Classifier: Development Status :: 4 - Beta
Classifier: Environment :: Web Environment
Classifier: Environment :: Console
Classifier: Intended Audience :: Developers
Classifier: License :: OSI Approved :: MIT License
Classifier: Operating System :: OS Independent
Classifier: Programming Language :: Python
Classifier: Programming Language :: Python :: 2.5
Classifier: Programming Language :: Python :: 2.6
Classifier: Programming Language :: Python :: 2.7
Classifier: Programming Language :: Python :: 3
Classifier: Programming Language :: Python :: 3.3
Classifier: Framework :: Django
Classifier: Topic :: Software Development :: Testing
Classifier: Topic :: Database
Requires-Dist: faker (>=0.0.4)
Requires-Dist: Django (>=1.4)
Requires-Dist: six (>=1.10.0)
